LICENSE
MANIFEST.in
README.rst
setup.py
pnet/__init__.py
pnet/checksum.py
pnet/hwaddress.py
pnet.egg-info/PKG-INFO
pnet.egg-info/SOURCES.txt
pnet.egg-info/dependency_links.txt
pnet.egg-info/top_level.txt
pnet/packet/__init__.py
pnet/packet/ethernet.py
pnet/packet/ipv4.py
pnet/packet/packet.py
pnet/packet/sll.py
pnet/packet/udp.py
tests/__init__.py
tests/test_checksum.py
tests/test_hwaddress.py
tests/test_serialization.py