Metadata-Version: 1.1
Name: pnet
Version: 0.0.1
Summary: Fast zero-copy packet creating and parsing module
Home-page: https://github.com/vodik/pnet
Author: Simon Gomizelj
Author-email: simon@vodik.xyz
License: Apache 2
Platform: UNKNOWN
Classifier: Development Status :: 4 - Beta
Classifier: Intended Audience :: Developers
Classifier: Programming Language :: Python
Classifier: Programming Language :: Python :: 3.4
Classifier: Programming Language :: Python :: 3.5
Classifier: Programming Language :: Python :: 3.6
Classifier: Programming Language :: Python :: Implementation :: CPython
Classifier: Operating System :: OS Independent
Classifier: License :: OSI Approved :: Apache Software License
